fastapi_dependency_manager/__init__.py
fastapi_dependency_manager/cli.py
fastapi_dependency_manager/main.py
fastapi_dependency_manager-1.0.4.dist-info/METADATA
fastapi_dependency_manager-1.0.4.dist-info/WHEEL
fastapi_dependency_manager-1.0.4.dist-info/entry_points.txt
fastapi_dependency_manager-1.0.4.dist-info/top_level.txt
fastapi_dependency_manager-1.0.4.dist-info/RECORD
