Metadata-Version: 2.2
Name: fastapi_dependency_manager
Version: 1.0.4
Summary: API to manage and upload Python dependencies
Home-page: https://github.com/Kanav-1822/fastapi-dependency-manager
Author: Kanav Arora
Author-email: kanavlt885@gmail.com
Classifier: Programming Language :: Python :: 3
Classifier: License :: OSI Approved :: MIT License
Classifier: Operating System :: OS Independent
Requires-Python: >=3.6
Requires-Dist: fastapi
Requires-Dist: uvicorn
Requires-Dist: azure-storage-blob
Requires-Dist: python-dotenv
Requires-Dist: retry
Requires-Dist: aiofiles
Requires-Dist: pydantic
Requires-Dist: requests
Requires-Dist: typer
Requires-Dist: rich
Requires-Dist: tqdm
Dynamic: author
Dynamic: author-email
Dynamic: classifier
Dynamic: home-page
Dynamic: requires-dist
Dynamic: requires-python
Dynamic: summary
